D_flipflop/rtl/dff.v
module dff(
    input d,
    input clk,
    output reg q
);

    always @(posedge clk)
    begin
        q <= d;
    end 

endmodule

D_flipflop/tb/dff_tb.v
module dff_tb();

    reg d;
    reg clk;
    wire q;

    dff uut (
        .d(d),
        .clk(clk),
        .q(q)
    );

    initial begin
        clk = 0;
        forever #5 clk = ~clk;
    end

    initial begin

        $dumpfile("wave.vcd");
        $dumpvars(0, dff_tb);
        
        d = 0; #10;
        d = 1; #10;
        d = 0; #10;
        d = 1; #10;
        d = 0; #10;
        $finish;
    end
endmodule

D_flipflop/wave.vcd
$date
	Tue Jun 16 12:52:53 2026
$end
$version
	Icarus Verilog
$end
$timescale
	1s
$end
$scope module dff_tb $end
$var wire 1 ! q $end
$var reg 1 " clk $end
$var reg 1 # d $end
$scope module uut $end
$var wire 1 " clk $end
$var wire 1 # d $end
$var reg 1 ! q $end
$upscope $end
$upscope $end
$enddefinitions $end
#0
$dumpvars
0#
0"
x!
$end
#5
0!
1"
#10
0"
1#
#15
1!
1"
#20
0"
0#
#25
0!
1"
#30
0"
1#
#35
1!
1"
#40
0"
0#
#45
0!
1"
