Serial_in_shiftregister/rtl/reg4bit.v
module reg4bit(
    input clk,
    input rst,
    input d,
    output reg [3:0] q
);

    always @(posedge clk)
    begin 
        if(rst)
            q <= 4'b0000;
        else
            q <= {q[2:0], d};
    end
endmodule

Serial_in_shiftregister/tb/reg4bit_tb.v
module reg4bit_tb ();
    reg clk;
    reg rst;
    reg d;
    wire [3:0] q;

    reg4bit uut (
        .clk(clk),
        .rst(rst),
        .d(d),
        .q(q)
    );

    initial begin
        clk = 0;
        forever #5 clk = ~clk;
    end

    initial begin
        $dumpfile("wave.vcd");
        $dumpvars(0, reg4bit_tb);
        
        rst = 1; 
        d = 0; 
        #10;
        rst = 0; 
        d = 1; #10;
        d = 0; #10;
        d = 1; #10;
        d = 1; #10;
        $finish;
    end
endmodule

Serial_in_shiftregister/wave.vcd
$date
	Tue Jun 16 13:48:11 2026
$end
$version
	Icarus Verilog
$end
$timescale
	1s
$end
$scope module reg4bit_tb $end
$var wire 4 ! q [3:0] $end
$var reg 1 " clk $end
$var reg 1 # d $end
$var reg 1 $ rst $end
$scope module uut $end
$var wire 1 " clk $end
$var wire 1 # d $end
$var wire 1 $ rst $end
$var reg 4 % q [3:0] $end
$upscope $end
$upscope $end
$enddefinitions $end
#0
$dumpvars
bx %
1$
0#
0"
bx !
$end
#5
b0 !
b0 %
1"
#10
0"
1#
0$
#15
b1 !
b1 %
1"
#20
0"
0#
#25
b10 !
b10 %
1"
#30
0"
1#
#35
b101 !
b101 %
1"
#40
0"
#45
b1011 !
b1011 %
1"
