4bitregister/rtl/reg4bit.v
module reg4bit(
    input [3:0] d,
    input clk,
    output reg [3:0] q
);
    always @(posedge clk)
    begin 
        q[3:0] <= d[3:0];
    end
endmodule

4bitregister/tb/reg4bit_tb.v
module reg4bit_tb();
    
    reg [3:0] d;
    reg clk;
    wire [3:0] q;

    reg4bit uut (
        .d(d),
        .clk(clk),
        .q(q)
    );

    initial begin 
        
        clk = 0;
        forever #5 clk = ~clk;
    end

    initial begin 
        $dumpfile("wave.vcd");
        $dumpvars(0, reg4bit_tb);
        
        d = 4'b0000; #10;
        d = 4'b0001; #10;
        d = 4'b0010; #10;
        d = 4'b0011; #10;
        d = 4'b0100; #10;
        d = 4'b0101; #10;
        d = 4'b0110; #10;
        d = 4'b0111; #10;
        d = 4'b1000; #10;
        d = 4'b1001; #10;
        d = 4'b1010; #10;
        d = 4'b1011; #10;
        d = 4'b1100; #10;
        d = 4'b1101; #10;
        d = 4'b1110; #10;
        d = 4'b1111; #10;
        $finish;
    end
endmodule

4bitregister/wave.vcd
$date
	Tue Jun 16 13:07:24 2026
$end
$version
	Icarus Verilog
$end
$timescale
	1s
$end
$scope module reg4bit_tb $end
$var wire 4 ! q [3:0] $end
$var reg 1 " clk $end
$var reg 4 # d [3:0] $end
$scope module uut $end
$var wire 1 " clk $end
$var wire 4 $ d [3:0] $end
$var reg 4 % q [3:0] $end
$upscope $end
$upscope $end
$enddefinitions $end
#0
$dumpvars
bx %
b0 $
b0 #
0"
bx !
$end
#5
b0 !
b0 %
1"
#10
0"
b1 #
b1 $
#15
b1 !
b1 %
1"
#20
0"
b10 #
b10 $
#25
b10 !
b10 %
1"
#30
0"
b11 #
b11 $
#35
b11 !
b11 %
1"
#40
0"
b100 #
b100 $
#45
b100 !
b100 %
1"
#50
0"
b101 #
b101 $
#55
b101 !
b101 %
1"
#60
0"
b110 #
b110 $
#65
b110 !
b110 %
1"
#70
0"
b111 #
b111 $
#75
b111 !
b111 %
1"
#80
0"
b1000 #
b1000 $
#85
b1000 !
b1000 %
1"
#90
0"
b1001 #
b1001 $
#95
b1001 !
b1001 %
1"
#100
0"
b1010 #
b1010 $
#105
b1010 !
b1010 %
1"
#110
0"
b1011 #
b1011 $
#115
b1011 !
b1011 %
1"
#120
0"
b1100 #
b1100 $
#125
b1100 !
b1100 %
1"
#130
0"
b1101 #
b1101 $
#135
b1101 !
b1101 %
1"
#140
0"
b1110 #
b1110 $
#145
b1110 !
b1110 %
1"
#150
0"
b1111 #
b1111 $
#155
b1111 !
b1111 %
1"
