ALU4bit/rtl/alu.v
module alu(
    input [3:0] a,
    input [3:0] b,
    input [2:0] sel,
    output reg [3:0] y,
    output reg carry
);
    
    always@(*)
    begin
        case(sel)
            3'b000: {carry, y} = a + b; 
            3'b001: {carry, y} = a - b; 
            3'b010: y = a & b;         
            3'b011: y = a | b;          
            3'b100: y = a ^ b;          
            3'b101: y = ~a;             
            3'b110: y = a << 1;         
            3'b111: y = a >> 1;      
          default: {carry, y} = 5'b00000;
        endcase
    end

endmodule

ALU4bit/tb/alu_tb.v
module alu_tb();
    reg [3:0] a;
    reg [3:0] b;
    reg [2:0] sel;
    wire [3:0] y;

    alu uut (
        .a(a),
        .b(b),
        .sel(sel),
        .y(y)
    );

    initial begin
        $dumpfile("wave.vcd");
        $dumpvars(0, alu_tb);
        
        a = 4'b0001; b = 4'b0010; sel = 3'b000; #10; 
        a = 4'b0100; b = 4'b0011; sel = 3'b001; #10; 
        a = 4'b0011; b = 4'b0101; sel = 3'b010; #10; 
        a = 4'b0110; b = 4'b0011; sel = 3'b011; #10; 
        a = 4'b1001; b = 4'b0100; sel = 3'b100; #10; 
        a = 4'b1010; b = 4'b0011; sel = 3'b101; #10; 
        a = 4'b1100; b = 4'b0000; sel = 3'b110; #10; 
        a = 4'b1111; b = 4'b0000; sel = 3'b111; #10; 
        
        $finish;
    end
endmodule

ALU4bit/wave.vcd
$date
	Tue Jun 16 14:03:08 2026
$end
$version
	Icarus Verilog
$end
$timescale
	1s
$end
$scope module alu_tb $end
$var wire 4 ! y [3:0] $end
$var reg 4 " a [3:0] $end
$var reg 4 # b [3:0] $end
$var reg 3 $ sel [2:0] $end
$scope module uut $end
$var wire 4 % a [3:0] $end
$var wire 4 & b [3:0] $end
$var wire 3 ' sel [2:0] $end
$var reg 1 ( carry $end
$var reg 4 ) y [3:0] $end
$upscope $end
$upscope $end
$enddefinitions $end
#0
$dumpvars
b11 )
0(
b0 '
b10 &
b1 %
b0 $
b10 #
b1 "
b11 !
$end
#10
b1 !
b1 )
b1 $
b1 '
b11 #
b11 &
b100 "
b100 %
#20
b10 $
b10 '
b101 #
b101 &
b11 "
b11 %
#30
b111 !
b111 )
b11 $
b11 '
b11 #
b11 &
b110 "
b110 %
#40
b1101 !
b1101 )
b100 $
b100 '
b100 #
b100 &
b1001 "
b1001 %
#50
b101 !
b101 )
b101 $
b101 '
b11 #
b11 &
b1010 "
b1010 %
#60
b1000 !
b1000 )
b110 $
b110 '
b0 #
b0 &
b1100 "
b1100 %
#70
b111 !
b111 )
b111 $
b111 '
b1111 "
b1111 %
